Workbook

Sheet Assumptions
A1: KYC Business Case | Model Assumptions
A2: Blue cells = inputs you can change to run scenarios. Black = formulas. Green = cross-sheet links.
A4: Category | B4: Parameter | C4: Value | D4: Unit | E4: Source / Note
A5: Volume | B5: Annual new customer onboardings completed | C5: 150000 | D5: customers/yr | E5: Internal estimate
A6: Volume | B6: Account applications started (derived) | C6: =C5/(1-C15) -> -1006.7114 | D6: applications | E6: Formula: completed / (1 - abandonment rate)
A7: Costs | B7: Current manual KYC cost per verification | C7: 30 | D7: CAD $/customer | E7: Industry est. (KYC2020; range $25-50, mid-point)
A8: Costs | B8: AI platform cost per verification | C8: 7 | D8: CAD $/customer | E8: Industry est. (SaaS vendors; range $5-10, mid-point)
A9: Costs | B9: Cost per false positive investigation | C9: 25 | D9: CAD $/alert | E9: Internal est. (25 min analyst time @ CAD $60/hr loaded)
A10: Compliance | B10: Current AML false positive rate | C10: 0.6 | D10: % of alerts | E10: KYC2020 research; published range 42-95%
A11: Compliance | B11: AI false positive rate reduction | C11: 0.55 | D11: % reduction | E11: Published vendor benchmarks; range 50-66%
A12: Customer | B12: Current account abandonment rate | C12: 0.5 | D12: % of starts | E12: DocuSign / CBA Canadian banking research
A13: Customer | B13: AI-assisted abandonment rate (target) | C13: 0.3 | D13: % of starts | E13: Conservative estimate; some vendors achieve <20%
A14: Customer | B14: Revenue capture rate (of additional completions) | C14: 0.25 | D14: % captured | E14: Conservative; accounts for customers acquired elsewhere
A15: Customer | B15: Avg first-year net revenue per new account | C15: 150 | D15: CAD $/account | E15: Conservative internal estimate; excl. lifetime value
A16: Platform Costs | B16: Platform licensing (annual SaaS) | C16: 600000 | D16: CAD $/yr | E16: SaaS estimate based on Onfido / Trulioo published ranges
A17: Platform Costs | B17: Integration and implementation (one-time) | C17: 800000 | D17: CAD $ | E17: Technology estimate; API integration + build
A18: Platform Costs | B18: Change management and training (one-time) | C18: 200000 | D18: CAD $ | E18: HR / Change Management estimate
... A25: Process Opt. | B25: Process optimization efficiency gain | C25: 0.15 | D25: % cost reduction | E25: Conservative estimate; addresses process only, not fraud
A27: COLOUR LEGEND
A28: Blue text = Hardcoded input (change to run scenarios)
A29: Black text = Formula (do not edit)
A30: Green text = Cross-sheet reference (do not edit)

Sheet Current State
A1: Current State | Annual Cost Analysis
A2: Quantifies the total cost of maintaining the existing manual KYC process at current volumes.
A4: Cost Category | B4: Calculation | C4: Annual Cost (CAD) | D4: Notes
A5: KYC Operational Cost | B5: =Assumptions!C5*Assumptions!C7 -> 4500000 | C5: =Assumptions!C5*Assumptions!C7 -> 4500000 | D5: Annual verifications x manual cost per check
A6: AML False Positive Investigation Cost | B6: =Assumptions!C5*Assumptions!C10*Assumptions!C9 -> 2250000 | C6: =Assumptions!C5*Assumptions!C10*Assumptions!C9 -> 2250000 | D6: Verifications x false positive rate x analyst cost per alert
A7: Lost Revenue from Account Abandonment | B7: =(Assumptions!C6-Assumptions!C5)*Assumptions!C14*Assumptions!C15 -> -5662751.7 | C7: =(Assumptions!C6-Assumptions!C5)*Assumptions!C14*Assumptions!C15 -> -5662751.7 | D7: Lost completions x capture rate x avg first-year revenue
A8: Risk-Adjusted Regulatory Penalty Exposure | B8: =Assumptions!C22*Assumptions!C23 -> 750000 | C8: =Assumptions!C22*Assumptions!C23 -> 750000 | D8: Annual probability of FINTRAC violation x avg penalty
A9: TOTAL QUANTIFIED ANNUAL COST | C9: =SUM(C5:C8) -> 1837248.3 | D9: Excl. unquantified competitive revenue loss
A11: Key Observations
A12: False positive rate of 60% means most analyst screening time is wasted on non-suspicious activity.
A13: 50% account abandonment represents 150,000 lost applicants annually who started but did not complete onboarding.
A14: Regulatory exposure is not a fixed cost but a probabilistic risk that grows with each FINTRAC audit cycle.
A15: Total direct operational cost (rows 5-6) = CAD $6.75M/yr before risk adjustment and revenue loss.

Sheet Options Comparison
A1: Options Comparison | Status Quo vs Process Optimization vs AI-Assisted KYC Platform
A2: All financial values in CAD. Figures derived from Assumptions sheet.
A4: Metric | B4: Option A: Status Quo | C4: Option B: Process Optimization | D4: Option C: AI-Assisted KYC Platform (Recommended) | F4: Notes
A5: One-Time Investment | B5: =0 -> 0 | C5: =Assumptions!C24 -> 250000 | D5: =Assumptions!C17+Assumptions!C18+Assumptions!C19 -> 1150000 | F5: Platform: integration + change mgmt + UAT
A6: Annual Platform / Licensing Cost | B6: =0 -> 0 | C6: =0 -> 0 | D6: =Assumptions!C16+Assumptions!C20 -> 700000 | F6: SaaS licensing + maintenance
A7: Annual KYC Operational Cost | B7: =Assumptions!C5*Assumptions!C7 -> 4500000 | C7: =Assumptions!C5*Assumptions!C7*(1-Assumptions!C25) -> 3825000 | D7: =Assumptions!C5*Assumptions!C8 -> 1050000 | F7: AI: per-verification cost drops to CAD $7
A8: Annual False Positive Cost | B8: =Assumptions!C5*Assumptions!C10*Assumptions!C9 -> 2250000 | C8: =Assumptions!C5*Assumptions!C10*Assumptions!C9 -> 2250000 | D8: =Assumptions!C5*Assumptions!C10*(1-Assumptions!C11)*Assumptions!C9 -> 1012500 | F8: AI reduces false positive rate by 55%
A9: Annual Revenue Recovery | B9: =0 -> 0 | C9: =0 -> 0 | D9: =(Assumptions!C6-Assumptions!C5)*(Assumptions!C12-Assumptions!C13)/(1-Assumptions!C12)*Assumptions!C14*Assumptions!C15 -> -2265100.7 | F9: Additional completions from lower abandonment rate
A10: Risk-Adj. Regulatory Penalty | B10: =Assumptions!C22*Assumptions!C23 -> 750000 | C10: =Assumptions!C22*Assumptions!C23*0.7 -> 525000 | D10: =Assumptions!C22*Assumptions!C23*0.1 -> 75000 | F10: AI: 90% reduction in regulatory exposure
A11: Annual Net Cost (Costs minus Benefits) | B11: =C7+C8+C10 -> 6600000 | C11: =B5/5+C7+C8+C10 -> 6600000 | D11: =D6+D7+D8-D9+D10 -> 5102600.7 | F11: Lower = better
A13: VERDICT | B13: Not viable. Regulatory non-compliance is unacceptable. | C13: Insufficient. Defers full solution at additional cost. | D13: RECOMMENDED. Only option satisfying all three dimensions.

Sheet Cost-Benefit Model
A1: Cost-Benefit Model | AI-Assisted KYC Platform | 3-Year Projection
A2: Year 0 = implementation period. Year 1-3 = operating years. All values CAD.
A4: Item | B4: Year 0 (Implementation) | C4: Year 1 | D4: Year 2 | E4: Year 3 | F4: 3-Year Total | G4: Notes
A6: ONE-TIME INVESTMENT COSTS
A7: Platform integration and implementation | B7: =-Assumptions!C17 -> -800000 | C7: =0 -> 0 | D7: =0 -> 0 | E7: =0 -> 0 | F7: =SUM(B7:E7) -> -800000 | G7: One-time; Year 0 only
A8: Change management and training | B8: =-Assumptions!C18 -> -200000 | C8: =0 -> 0 | D8: =0 -> 0 | E8: =0 -> 0 | F8: =SUM(B8:E8) -> -200000 | G8: One-time; Year 0 only
A9: Data migration, UAT, go-live support | B9: =-Assumptions!C19 -> -150000 | C9: =0 -> 0 | D9: =0 -> 0 | E9: =0 -> 0 | F9: =SUM(B9:E9) -> -150000 | G9: One-time; Year 0 only
A10: Total One-Time Investment | B10: =SUM(B7:B9) -> -1150000 | C10: =SUM(C7:C9) -> 0 | D10: =SUM(D7:D9) -> 0 | E10: =SUM(E7:E9) -> 0 | F10: =SUM(F7:F9) -> -1150000
A12: ANNUAL OPERATING COSTS
A13: Platform licensing (annual SaaS) | B13: =0 -> 0 | C13: =-Assumptions!C16 -> -600000 | D13: =-Assumptions!C16 -> -600000 | E13: =-Assumptions!C16 -> -600000 | F13: =SUM(B13:E13) -> -1800000 | G13: SaaS; begins Year 1
A14: Ongoing maintenance and support | B14: =0 -> 0 | C14: =-Assumptions!C20 -> -100000 | D14: =-Assumptions!C20 -> -100000 | E14: =-Assumptions!C20 -> -100000 | F14: =SUM(B14:E14) -> -300000 | G14: Annual vendor support
A15: AI platform cost per verification (net) | B15: =0 -> 0 | C15: =-Assumptions!C5*Assumptions!C8 -> -1050000 | D15: =-Assumptions!C5*Assumptions!C8 -> -1050000 | E15: =-Assumptions!C5*Assumptions!C8 -> -1050000 | F15: =SUM(B15:E15) -> -3150000 | G15: 150K verifications x CAD $7
A16: Total Annual Operating Costs | B16: =SUM(B13:B15) -> 0 | C16: =SUM(C13:C15) -> -1750000 | D16: =SUM(D13:D15) -> -1750000 | E16: =SUM(E13:E15) -> -1750000 | F16: =SUM(F13:F15) -> -5250000
A18: ANNUAL BENEFITS (SAVINGS + REVENUE)
A19: KYC operational cost savings vs manual | B19: =0 -> 0 | C19: =Assumptions!C5*(Assumptions!C7-Assumptions!C8) -> 3450000 | D19: =Assumptions!C5*(Assumptions!C7-Assumptions!C8) -> 3450000 | E19: =Assumptions!C5*(Assumptions!C7-Assumptions!C8) -> 3450000 | F19: =SUM(B19:E19) -> 10350000 | G19: CAD $30 - $7 = $23 saved per verification
A20: False positive reduction savings | B20: =0 -> 0 | C20: =Assumptions!C5*Assumptions!C10*Assumptions!C11*Assumptions!C9 -> 1237500 | D20: =Assumptions!C5*Assumptions!C10*Assumptions!C11*Assumptions!C9 -> 1237500 | E20: =Assumptions!C5*Assumptions!C10*Assumptions!C11*Assumptions!C9 -> 1237500 | F20: =SUM(B20:E20) -> 3712500 | G20: 55% fewer alerts x $25 analyst cost each
A21: Revenue recovery from reduced abandonment | B21: =0 -> 0 | C21: =(Assumptions!C6-Assumptions!C5)*(Assumptions!C12-Assumptions!C13)/(1-Assumptions!C12)*Assumptions!C14*Assumptions!C15 -> -2265100.7 | D21: =(Assumptions!C6-Assumptions!C5)*(Assumptions!C12-Assumptions!C13)/(1-Assumptions!C12)*Assumptions!C14*Assumptions!C15 -> -2265100.7 | E21: =(Assumptions!C6-Assumptions!C5)*(Assumptions!C12-Assumptions!C13)/(1-Assumptions!C12)*Assumptions!C14*Assumptions!C15 -> -2265100.7 | F21: =SUM(B21:E21) -> -6795302 | G21: Additional completions x capture rate x avg revenue
A22: Risk-adjusted regulatory penalty avoidance | B22: =0 -> 0 | C22: =Assumptions!C22*Assumptions!C23 -> 750000 | D22: =Assumptions!C22*Assumptions!C23 -> 750000 | E22: =Assumptions!C22*Assumptions!C23 -> 750000 | F22: =SUM(B22:E22) -> 2250000 | G22: 5% annual probability x CAD $15M avg penalty
A23: Total Annual Benefits | B23: =SUM(B19:B22) -> 0 | C23: =SUM(C19:C22) -> 3172399.3 | D23: =SUM(D19:D22) -> 3172399.3 | E23: =SUM(E19:E22) -> 3172399.3 | F23: =SUM(F19:F22) -> 9517198
A25: NET CASH FLOW (Benefits + Costs) | B25: =B23+B10+B16 -> -1150000 | C25: =C23+C10+C16 -> 1422399.3 | D25: =D23+D10+D16 -> 1422399.3 | E25: =E23+E10+E16 -> 1422399.3 | F25: =F23+F10+F16 -> 3117198 | G25: Positive = net benefit in that year
A26: CUMULATIVE CASH FLOW | B26: =B25 -> -1150000 | C26: =B26+C25 -> 272399.33 | D26: =C26+D25 -> 1694798.7 | E26: =D26+E25 -> 3117198 | F26: =E26 -> 3117198 | G26: Turns positive = payback achieved
A28: RETURN ON INVESTMENT SUMMARY
A29: Total Year 0 Investment | C29: =B10 -> -1150000 | G29: One-time implementation costs
A30: Year 1 Net Cash Flow | C30: =C25 -> 1422399.3 | G30: Benefits minus all Year 1 costs
A31: Annual Net Cash Flow (Year 2+) | C31: =D23+D16 -> 1422399.3 | G31: Recurring annual net benefit
A32: 3-Year NPV (discount rate from Assumptions) | C32: =C25/(1+Assumptions!C21)+D25/(1+Assumptions!C21)^2+E25/(1+Assumptions!C21)^3+B25 -> 2515661 | G32: Net present value; Year 0-3
A33: Approx. Payback Period (months) | C33: =-B10/((C25+D25+E25)/36) -> 9.7019168 | G33: Months to recover Year 0 investment
A34: 3-Year ROI | C34: =(C25+D25+E25-ABS(B10))/ABS(B10) -> 2.7106069 | G34: Net return over total investment

Sheet Sensitivity Analysis
A1: Sensitivity Analysis | Key Variable Scenarios
A2: Shows Year 1 Net Benefit and 3-Year NPV under different assumptions. Change Assumptions sheet inputs to see full model impact.
A4: Table A: Annual Volume Sensitivity (New Customer Onboardings)
A5: Scenario | B5: Annual Volume | C5: Annual Benefit (CAD) | D5: Annual Net (after platform costs) | E5: Notes
A6: Low Volume (-30%) | B6: =Assumptions!C5*0.7 -> 105000 | C6: =(Assumptions!C5*0.7)*(Assumptions!C7-Assumptions!C8)+(Assumptions!C5*0.7)*Assumptions!C10*Assumptions!C11*Assumptions!C9+Assumptions!C22*Assumptions!C23+((Assumptions!C5*0.7)/(1-Assumptions!C12)-(Assumptions!C5*0.7))*(Assumptions!C12-Assumptions!C13)/(1-Assumptions!C12)*Assumptions!C14*Assumptions!C15 -> 5606250 | D6: =C6-(Assumptions!C16+Assumptions!C20) -> 4906250
A7: Conservative (-15%) | B7: =Assumptions!C5*0.85 -> 127500 | C7: =(Assumptions!C5*0.85)*(Assumptions!C7-Assumptions!C8)+(Assumptions!C5*0.85)*Assumptions!C10*Assumptions!C11*Assumptions!C9+Assumptions!C22*Assumptions!C23+((Assumptions!C5*0.85)/(1-Assumptions!C12)-(Assumptions!C5*0.85))*(Assumptions!C12-Assumptions!C13)/(1-Assumptions!C12)*Assumptions!C14*Assumptions!C15 -> 6646875 | D7: =C7-(Assumptions!C16+Assumptions!C20) -> 5946875
A8: Base Case | B8: =Assumptions!C5 -> 150000 | C8: =(Assumptions!C5*1)*(Assumptions!C7-Assumptions!C8)+(Assumptions!C5*1)*Assumptions!C10*Assumptions!C11*Assumptions!C9+Assumptions!C22*Assumptions!C23+((Assumptions!C5*1)/(1-Assumptions!C12)-(Assumptions!C5*1))*(Assumptions!C12-Assumptions!C13)/(1-Assumptions!C12)*Assumptions!C14*Assumptions!C15 -> 7687500 | D8: =C8-(Assumptions!C16+Assumptions!C20) -> 6987500 | E8: Base case
A9: Optimistic (+15%) | B9: =Assumptions!C5*1.15 -> 172500 | C9: =(Assumptions!C5*1.15)*(Assumptions!C7-Assumptions!C8)+(Assumptions!C5*1.15)*Assumptions!C10*Assumptions!C11*Assumptions!C9+Assumptions!C22*Assumptions!C23+((Assumptions!C5*1.15)/(1-Assumptions!C12)-(Assumptions!C5*1.15))*(Assumptions!C12-Assumptions!C13)/(1-Assumptions!C12)*Assumptions!C14*Assumptions!C15 -> 8728125 | D9: =C9-(Assumptions!C16+Assumptions!C20) -> 8028125
A10: High Growth (+30%) | B10: =Assumptions!C5*1.3 -> 195000 | C10: =(Assumptions!C5*1.3)*(Assumptions!C7-Assumptions!C8)+(Assumptions!C5*1.3)*Assumptions!C10*Assumptions!C11*Assumptions!C9+Assumptions!C22*Assumptions!C23+((Assumptions!C5*1.3)/(1-Assumptions!C12)-(Assumptions!C5*1.3))*(Assumptions!C12-Assumptions!C13)/(1-Assumptions!C12)*Assumptions!C14*Assumptions!C15 -> 9768750 | D10: =C10-(Assumptions!C16+Assumptions!C20) -> 9068750
A12: Table B: Platform Cost Sensitivity (Annual Licensing)
A13: Scenario | B13: Annual Platform Cost (CAD) | C13: Year 1 Net Benefit | D13: Payback Period (months) | E13: Notes
A14: Below Estimate (-20%) | B14: =Assumptions!C16*0.8 -> 480000 | C14: =Assumptions!C5*(Assumptions!C7-Assumptions!C8)+Assumptions!C5*Assumptions!C10*Assumptions!C11*Assumptions!C9+Assumptions!C22*Assumptions!C23+(Assumptions!C6-Assumptions!C5)*(Assumptions!C12-Assumptions!C13)/(1-Assumptions!C12)*Assumptions!C14*Assumptions!C15-(Assumptions!C16*0.8)-Assumptions!C20 -> 2592399.3 | D14: =-(Assumptions!C17+Assumptions!C18+Assumptions!C19)/(C14)*12 -> -5.323254
A15: Base Case | B15: =Assumptions!C16 -> 600000 | C15: =Assumptions!C5*(Assumptions!C7-Assumptions!C8)+Assumptions!C5*Assumptions!C10*Assumptions!C11*Assumptions!C9+Assumptions!C22*Assumptions!C23+(Assumptions!C6-Assumptions!C5)*(Assumptions!C12-Assumptions!C13)/(1-Assumptions!C12)*Assumptions!C14*Assumptions!C15-(Assumptions!C16*1)-Assumptions!C20 -> 2472399.3 | D15: =-(Assumptions!C17+Assumptions!C18+Assumptions!C19)/(C15)*12 -> -5.5816226 | E15: Base case
A16: Above Estimate (+20%) | B16: =Assumptions!C16*1.2 -> 720000 | C16: =Assumptions!C5*(Assumptions!C7-Assumptions!C8)+Assumptions!C5*Assumptions!C10*Assumptions!C11*Assumptions!C9+Assumptions!C22*Assumptions!C23+(Assumptions!C6-Assumptions!C5)*(Assumptions!C12-Assumptions!C13)/(1-Assumptions!C12)*Assumptions!C14*Assumptions!C15-(Assumptions!C16*1.2)-Assumptions!C20 -> 2352399.3 | D16: =-(Assumptions!C17+Assumptions!C18+Assumptions!C19)/(C16)*12 -> -5.8663509
A17: Above Estimate (+40%) | B17: =Assumptions!C16*1.4 -> 840000 | C17: =Assumptions!C5*(Assumptions!C7-Assumptions!C8)+Assumptions!C5*Assumptions!C10*Assumptions!C11*Assumptions!C9+Assumptions!C22*Assumptions!C23+(Assumptions!C6-Assumptions!C5)*(Assumptions!C12-Assumptions!C13)/(1-Assumptions!C12)*Assumptions!C14*Assumptions!C15-(Assumptions!C16*1.4)-Assumptions!C20 -> 2232399.3 | D17: =-(Assumptions!C17+Assumptions!C18+Assumptions!C19)/(C17)*12 -> -6.1816897
A19: Key Insight: Even in the high-cost, low-volume scenario, the AI-Assisted KYC Platform remains cash-positive in Year 1 due to the magnitude of operational savings from eliminating manual verification and false positive investigation costs.
